tests/__init__.py
wagtailcomments/__init__.py
wagtailcomments/_version.py
wagtailcomments/conf.py
wagtailcomments/forms.py
wagtailcomments/jinja2tags.py
wagtailcomments/modeladmin.py
wagtailcomments/models.py
wagtailcomments/registry.py
wagtailcomments/templatetags.py
wagtailcomments/urls.py
wagtailcomments/utils.py
wagtailcomments/views.py
wagtailcomments/wagtail_hooks.py
wagtailcomments/basic/__init__.py
wagtailcomments/basic/apps.py
wagtailcomments/basic/forms.py
wagtailcomments/basic/jinja2tags.py
wagtailcomments/basic/models.py
wagtailcomments/basic/wagtail_hooks.py
wagtailcomments/basic/migrations/0001_initial.py
wagtailcomments/basic/migrations/__init__.py
wagtailcomments/basic/templatetags/__init__.py
wagtailcomments/basic/templatetags/wagtailcomments_tags.py
wagtailcomments/templates/wagtailcomments/add_comment.html
wagtailcomments/templates/wagtailcomments/comments_summary.html
wagtailcomments-0.2.1.dist-info/DESCRIPTION.rst
wagtailcomments-0.2.1.dist-info/METADATA
wagtailcomments-0.2.1.dist-info/RECORD
wagtailcomments-0.2.1.dist-info/WHEEL
wagtailcomments-0.2.1.dist-info/metadata.json
wagtailcomments-0.2.1.dist-info/top_level.txt
