Metadata-Version: 2.0
Name: wagtailcomments
Version: 0.2.1
Summary: UNKNOWN
Home-page: https://github.com/takeflight/wagtailcomments
Author: Takeflight
Author-email: tim@takeflight.com.au
License: BSD License
Platform: UNKNOWN
Classifier: Environment :: Web Environment
Classifier: Intended Audience :: Developers
Classifier: Operating System :: OS Independent
Classifier: Programming Language :: Python
Classifier: Programming Language :: Python :: 3
Classifier: Programming Language :: Python :: 3.4
Classifier: Programming Language :: Python :: 3.5
Classifier: Framework :: Django
Classifier: License :: OSI Approved :: BSD License
Requires-Dist: Django (>=1.9)
Requires-Dist: django-enumchoicefield (>=0.5.2)
Requires-Dist: django-ipware
Requires-Dist: wagtail (>=1.5)
